immukv/__init__.py
immukv/client.py
immukv/json_helpers.py
immukv/py.typed
immukv/types.py
immukv/_internal/__init__.py
immukv/_internal/s3_client.py
immukv/_internal/s3_helpers.py
immukv/_internal/s3_types.py
immukv-0.1.15.dist-info/METADATA
immukv-0.1.15.dist-info/WHEEL
immukv-0.1.15.dist-info/top_level.txt
immukv-0.1.15.dist-info/RECORD
