Metadata-Version: 2.4
Name: immukv
Version: 0.1.15
Summary: Lightweight immutable key-value store using S3 versioning
Author: ImmuKV Contributors
License: MIT
Classifier: Development Status :: 3 - Alpha
Classifier: Intended Audience :: Developers
Classifier: License :: OSI Approved :: MIT License
Classifier: Programming Language :: Python :: 3
Classifier: Programming Language :: Python :: 3.11
Classifier: Programming Language :: Python :: 3.12
Requires-Python: >=3.11
Requires-Dist: boto3>=1.28.0
Provides-Extra: dev
Requires-Dist: pytest>=7.4.0; extra == "dev"
Requires-Dist: pytest-asyncio>=0.21.0; extra == "dev"
Requires-Dist: mypy>=1.5.0; extra == "dev"
Requires-Dist: boto3-stubs[s3]>=1.28.0; extra == "dev"
Requires-Dist: black>=23.7.0; extra == "dev"
Requires-Dist: ruff>=0.0.286; extra == "dev"
